{
  "variables": [
    {
      "variable": "ACT",
      "candidates": [
        {
          "sheet_name": "Balance Sheet",
          "row_label": "Total current assets",
          "why": "Exact match for total current assets on the balance sheet.",
          "confidence": 0.99
        },
        {
          "sheet_name": "Balance Sheet",
          "row_label": "Balancing Item - Current Assets",
          "why": "Balancing/subtotal line, not preferred over the explicitly reported total.",
          "confidence": 0.2
        },
        {
          "sheet_name": "Balance Sheet",
          "row_label": "Total non-current assets",
          "why": "Wrong section; non-current assets are not current assets.",
          "confidence": 0.01
        }
      ],
      "final_choice": [
        {
          "sheet_name": "Balance Sheet",
          "row_label": "Total current assets"
        }
      ],
      "needs_manual_review": false,
      "notes": "Selected the explicit reported current-assets total."
    },
    {
      "variable": "CHE",
      "candidates": [
        {
          "sheet_name": "Balance Sheet",
          "row_label": "Cash and cash equivalents",
          "why": "Exact balance-sheet cash line; preferred over cash-flow beginning/end balances.",
          "confidence": 0.99
        },
        {
          "sheet_name": "Cash Flow",
          "row_label": "Cash and cash equivalents at end of period",
          "why": "Cash-flow reconciliation line, but CHE should come from the balance sheet when available.",
          "confidence": 0.6
        },
        {
          "sheet_name": "Cash Flow",
          "row_label": "Cash and cash equivalents at beginning of period",
          "why": "Not the balance-sheet period-end cash target.",
          "confidence": 0.2
        }
      ],
      "final_choice": [
        {
          "sheet_name": "Balance Sheet",
          "row_label": "Cash and cash equivalents"
        }
      ],
      "needs_manual_review": false,
      "notes": "Used the balance-sheet cash line. Duplicate label appears in preview, but the explicit balance-sheet row label is still the correct choice."
    },
    {
      "variable": "LCT",
      "candidates": [
        {
          "sheet_name": "Balance Sheet",
          "row_label": "Total current liabilities",
          "why": "Exact match for total current liabilities.",
          "confidence": 0.99
        },
        {
          "sheet_name": "Balance Sheet",
          "row_label": "Other current liabilities",
          "why": "Component of current liabilities, not the total.",
          "confidence": 0.25
        },
        {
          "sheet_name": "Balance Sheet",
          "row_label": "Total non-current liabilities",
          "why": "Wrong maturity bucket.",
          "confidence": 0.01
        }
      ],
      "final_choice": [
        {
          "sheet_name": "Balance Sheet",
          "row_label": "Total current liabilities"
        }
      ],
      "needs_manual_review": false,
      "notes": "Selected the explicit total current liabilities line."
    },
    {
      "variable": "STD",
      "candidates": [
        {
          "sheet_name": "Balance Sheet",
          "row_label": "Short-term interest-bearing liabilities",
          "why": "Best direct balance-sheet measure of short-term debt; clean interest-bearing current borrowing line and excludes leases.",
          "confidence": 0.97
        },
        {
          "sheet_name": "Balance Sheet",
          "row_label": "Liabilities due within 1 Year",
          "why": "Debt-maturity schedule line, but potentially broader/less clean than the direct current interest-bearing liabilities line.",
          "confidence": 0.55
        },
        {
          "sheet_name": "Balance Sheet",
          "row_label": "Current portion of long-term interest-bearing liabilities",
          "why": "Would be relevant for current maturities of long-term debt, but shown as blank in preview and may not be consistently populated.",
          "confidence": 0.45
        },
        {
          "sheet_name": "Balance Sheet",
          "row_label": "Financial Leasing due within 1 Year",
          "why": "Explicitly lease-related and should be excluded from STD under the baseline rule.",
          "confidence": 0.01
        }
      ],
      "final_choice": [
        {
          "sheet_name": "Balance Sheet",
          "row_label": "Short-term interest-bearing liabilities"
        }
      ],
      "needs_manual_review": false,
      "notes": "Chose a confident label outside the shortlist because it is the cleanest direct short-term debt line and excludes lease liabilities."
    },
    {
      "variable": "TXP",
      "candidates": [
        {
          "sheet_name": "Balance Sheet",
          "row_label": "Current income tax liabilities",
          "why": "Best direct match for taxes payable/current tax liabilities payable.",
          "confidence": 0.98
        },
        {
          "sheet_name": "Balance Sheet",
          "row_label": "VAT and other indirect tax payables",
          "why": "Indirect tax payable, but narrower and not the standard income-tax-payable target.",
          "confidence": 0.45
        },
        {
          "sheet_name": "Balance Sheet",
          "row_label": "Current income tax assets",
          "why": "Tax asset, opposite of payable/liability.",
          "confidence": 0.01
        }
      ],
      "final_choice": [
        {
          "sheet_name": "Balance Sheet",
          "row_label": "Current income tax liabilities"
        }
      ],
      "needs_manual_review": false,
      "notes": "Selected a confident label outside the shortlist because TXP targets payable/current tax liabilities, and this is the clearest match."
    },
    {
      "variable": "PPEGT",
      "candidates": [
        {
          "sheet_name": "Balance Sheet",
          "row_label": "Property, plant and equipment",
          "why": "Exact total/net PPE line on the balance sheet; preferred.",
          "confidence": 0.99
        },
        {
          "sheet_name": "Balance Sheet",
          "row_label": "Other Tangible Fixed Assets, Net",
          "why": "Only a component/alternative tangible-assets line, not as clean as the total PPE line.",
          "confidence": 0.2
        },
        {
          "sheet_name": "Cash Flow",
          "row_label": "Sale of PPE and Non-Current Financial Investments",
          "why": "Cash-flow line, not a balance-sheet PPE stock measure.",
          "confidence": 0.01
        }
      ],
      "final_choice": [
        {
          "sheet_name": "Balance Sheet",
          "row_label": "Property, plant and equipment"
        }
      ],
      "needs_manual_review": false,
      "notes": "Used the explicit balance-sheet PPE total."
    },
    {
      "variable": "AT",
      "candidates": [
        {
          "sheet_name": "Balance Sheet",
          "row_label": "Total Assets",
          "why": "Exact match for total assets.",
          "confidence": 0.99
        },
        {
          "sheet_name": "Balance Sheet",
          "row_label": "Total shareholders equity and liabilities",
          "why": "Balances to assets but is not the preferred assets label.",
          "confidence": 0.35
        },
        {
          "sheet_name": "Balance Sheet",
          "row_label": "Other LT Assets, Total/No Breakdown",
          "why": "Not total assets.",
          "confidence": 0.01
        }
      ],
      "final_choice": [
        {
          "sheet_name": "Balance Sheet",
          "row_label": "Total Assets"
        }
      ],
      "needs_manual_review": false,
      "notes": "Selected the explicit total assets line."
    },
    {
      "variable": "OANCF",
      "candidates": [
        {
          "sheet_name": "Cash Flow",
          "row_label": "Net cash flows from operating activities",
          "why": "Exact net operating cash flow line; best match for OANCF.",
          "confidence": 0.99
        },
        {
          "sheet_name": "Cash Flow",
          "row_label": "Cash flows from operations",
          "why": "Operating cash flow before some cash items/working-capital effects in some formats; less clearly the final net operating cash flow line.",
          "confidence": 0.65
        }
      ],
      "final_choice": [
        {
          "sheet_name": "Cash Flow",
          "row_label": "Net cash flows from operating activities"
        }
      ],
      "needs_manual_review": false,
      "notes": "Preferred the explicit net cash flow from operating activities line over the broader 'Cash flows from operations' subtotal."
    }
  ]
}