{
  "variables": [
    {
      "variable": "ACT",
      "candidates": [
        {
          "sheet_name": "Balance Sheet",
          "row_label": "Total Current Assets",
          "why": "Exact match for total current assets on the balance sheet.",
          "confidence": 0.99
        },
        {
          "sheet_name": "Balance Sheet",
          "row_label": "Derivative instrument Tothtaelrf fixixeeddaasssseettss Current assets",
          "why": "Contains 'Current assets' but appears garbled and not a clean total.",
          "confidence": 0.12
        },
        {
          "sheet_name": "Balance Sheet",
          "row_label": "Balancing Item - Current Assets",
          "why": "Balancing line, not the reported total current assets.",
          "confidence": 0.02
        },
        {
          "sheet_name": "Balance Sheet",
          "row_label": "Balancing Item - Noncurrent Assets",
          "why": "Noncurrent assets balancing line, not current assets.",
          "confidence": 0.01
        }
      ],
      "final_choice": [
        {
          "sheet_name": "Balance Sheet",
          "row_label": "Total Current Assets"
        }
      ],
      "needs_manual_review": false,
      "notes": "Selected the explicit total current assets line."
    },
    {
      "variable": "CHE",
      "candidates": [
        {
          "sheet_name": "Balance Sheet",
          "row_label": "Cashandcashequivalents",
          "why": "Exact balance-sheet cash and cash equivalents line.",
          "confidence": 0.99
        },
        {
          "sheet_name": "Cash Flow",
          "row_label": "Cashandcashequivalentsat the beginningofthe period",
          "why": "Cash flow carryforward line, not the balance-sheet cash stock requested.",
          "confidence": 0.08
        },
        {
          "sheet_name": "Cash Flow",
          "row_label": "Cash andcash equivalentsat theendoftheperiod",
          "why": "Cash flow ending balance agrees numerically, but CHE should come from the balance sheet when available.",
          "confidence": 0.2
        },
        {
          "sheet_name": "Cash Flow",
          "row_label": "Exchange rate difference incashandcashequivalents",
          "why": "FX movement line, not cash balance.",
          "confidence": 0.01
        },
        {
          "sheet_name": "Cash Flow",
          "row_label": "Interest Paid - Cash",
          "why": "Cash interest flow, not cash balance.",
          "confidence": 0.0
        },
        {
          "sheet_name": "Cash Flow",
          "row_label": "Cash Interest Paid",
          "why": "Cash interest flow, not cash balance.",
          "confidence": 0.0
        },
        {
          "sheet_name": "Cash Flow",
          "row_label": "Cash Taxes Paid",
          "why": "Cash taxes flow, not cash balance.",
          "confidence": 0.0
        }
      ],
      "final_choice": [
        {
          "sheet_name": "Balance Sheet",
          "row_label": "Cashandcashequivalents"
        }
      ],
      "needs_manual_review": false,
      "notes": "Used the balance-sheet cash line."
    },
    {
      "variable": "LCT",
      "candidates": [
        {
          "sheet_name": "Balance Sheet",
          "row_label": "Totalcurrent liabilities",
          "why": "Exact total current liabilities line on the balance sheet.",
          "confidence": 0.99
        },
        {
          "sheet_name": "Balance Sheet",
          "row_label": "Other current liabilities",
          "why": "Component of current liabilities, not the total.",
          "confidence": 0.18
        },
        {
          "sheet_name": "Balance Sheet",
          "row_label": "Balancing Item - Current Liabilities",
          "why": "Balancing line, not the reported total.",
          "confidence": 0.02
        },
        {
          "sheet_name": "Balance Sheet",
          "row_label": "Other non-current liabilities",
          "why": "Non-current liabilities component, not current liabilities total.",
          "confidence": 0.01
        },
        {
          "sheet_name": "Balance Sheet",
          "row_label": "Balancing Item - Noncurrent Liabilities",
          "why": "Balancing line for non-current liabilities.",
          "confidence": 0.0
        },
        {
          "sheet_name": "Balance Sheet",
          "row_label": "Total non-current liabilities",
          "why": "Wrong maturity bucket.",
          "confidence": 0.0
        }
      ],
      "final_choice": [
        {
          "sheet_name": "Balance Sheet",
          "row_label": "Totalcurrent liabilities"
        }
      ],
      "needs_manual_review": false,
      "notes": "Selected the explicit total current liabilities line."
    },
    {
      "variable": "STD",
      "candidates": [
        {
          "sheet_name": "Balance Sheet",
          "row_label": "Current interest-bearing liabilities",
          "why": "Best match for current financing-related debt; appears to be the clean total short-term interest-bearing debt line.",
          "confidence": 0.87
        },
        {
          "sheet_name": "Balance Sheet",
          "row_label": "Current Portion of LT Debt",
          "why": "Would be a component of STD, but values are blank in preview and may not be the active reported label.",
          "confidence": 0.35
        },
        {
          "sheet_name": "Balance Sheet",
          "row_label": "Current Portion of Long-Term Debt including Capitalized Leases",
          "why": "Contains leases and should be excluded in baseline; also blank in preview.",
          "confidence": 0.08
        },
        {
          "sheet_name": "Balance Sheet",
          "row_label": "Capital Lease Maturities - Due within 1 Year",
          "why": "Explicitly lease-related and should be excluded from STD.",
          "confidence": 0.0
        }
      ],
      "final_choice": [
        {
          "sheet_name": "Balance Sheet",
          "row_label": "Current interest-bearing liabilities"
        }
      ],
      "needs_manual_review": false,
      "notes": "Chose a label outside the shortlist because it is the clearest reported current debt total. Excluded lease-specific rows per rule."
    },
    {
      "variable": "TXP",
      "candidates": [
        {
          "sheet_name": "Balance Sheet",
          "row_label": "Short-term tax liabilities",
          "why": "Best match for taxes payable/current tax liabilities.",
          "confidence": 0.96
        },
        {
          "sheet_name": "Balance Sheet",
          "row_label": "Tax Liabilities",
          "why": "Could refer to taxes payable, but preview is blank and less specific than the short-term tax line.",
          "confidence": 0.32
        },
        {
          "sheet_name": "Balance Sheet",
          "row_label": "Deferredtax liabilities",
          "why": "Deferred tax is non-current/non-payable in the accruals sense, so not TXP.",
          "confidence": 0.01
        },
        {
          "sheet_name": "Balance Sheet",
          "row_label": "Deferred Tax Liabilities",
          "why": "Deferred tax, not current taxes payable.",
          "confidence": 0.01
        }
      ],
      "final_choice": [
        {
          "sheet_name": "Balance Sheet",
          "row_label": "Short-term tax liabilities"
        }
      ],
      "needs_manual_review": false,
      "notes": "Selected the explicit short-term/current tax liability row."
    },
    {
      "variable": "PPEGT",
      "candidates": [
        {
          "sheet_name": "Balance Sheet",
          "row_label": "Equipment andmachinery",
          "why": "Best direct balance-sheet PPE line available; represents tangible fixed assets net of depreciation rather than intangibles or broader fixed-asset totals.",
          "confidence": 0.79
        },
        {
          "sheet_name": "Balance Sheet",
          "row_label": "Fixed Assets Gross",
          "why": "Gross fixed assets is not clean PPE total here because fixed assets section also includes investment properties and other assets, and gross would require accumulated depreciation adjustment.",
          "confidence": 0.33
        },
        {
          "sheet_name": "Balance Sheet",
          "row_label": "Equipment, Tools & Fittings",
          "why": "Would be PPE, but values are blank in preview and may not be the active row.",
          "confidence": 0.28
        },
        {
          "sheet_name": "Balance Sheet",
          "row_label": "Intangible assets",
          "why": "Not PPE.",
          "confidence": 0.0
        },
        {
          "sheet_name": "Cash Flow",
          "row_label": "Investments inintangible assets",
          "why": "Cash flow capex line for intangibles, not balance-sheet PPE stock.",
          "confidence": 0.0
        }
      ],
      "final_choice": [
        {
          "sheet_name": "Balance Sheet",
          "row_label": "Equipment andmachinery"
        }
      ],
      "needs_manual_review": false,
      "notes": "Chose a label outside the shortlist because it is the clearest tangible PPE stock on the balance sheet. Avoided 'Total fixed assets' since that includes investment properties and intangibles."
    },
    {
      "variable": "AT",
      "candidates": [
        {
          "sheet_name": "Balance Sheet",
          "row_label": "Total Assets",
          "why": "Exact match for total assets.",
          "confidence": 0.99
        }
      ],
      "final_choice": [
        {
          "sheet_name": "Balance Sheet",
          "row_label": "Total Assets"
        }
      ],
      "needs_manual_review": false,
      "notes": "Selected the explicit total assets line."
    },
    {
      "variable": "OANCF",
      "candidates": [
        {
          "sheet_name": "Cash Flow",
          "row_label": "Cash flow from operating activities",
          "why": "Exact match for operating cash flow / net cash from operating activities.",
          "confidence": 0.99
        }
      ],
      "final_choice": [
        {
          "sheet_name": "Cash Flow",
          "row_label": "Cash flow from operating activities"
        }
      ],
      "needs_manual_review": false,
      "notes": "Selected the explicit operating cash flow line."
    }
  ]
}