{
  "variables": [
    {
      "variable": "ACT",
      "candidates": [
        {
          "sheet_name": "Balance Sheet",
          "row_label": "Current Assets",
          "why": "Section header for current assets, but not the reported total value line.",
          "confidence": 0.23
        },
        {
          "sheet_name": "Balance Sheet",
          "row_label": "Other Current Assets - Total",
          "why": "Only a component of current assets, not total current assets.",
          "confidence": 0.06
        },
        {
          "sheet_name": "Balance Sheet",
          "row_label": "Other Current Assets",
          "why": "Only a component/category, not total current assets.",
          "confidence": 0.05
        },
        {
          "sheet_name": "Balance Sheet",
          "row_label": "Total Current Assets",
          "why": "Exact total current assets line on the balance sheet; best match for ACT.",
          "confidence": 0.99
        },
        {
          "sheet_name": "Balance Sheet",
          "row_label": "Working Capital excluding Other Current Assets & Liabilities",
          "why": "Derived metric, not total current assets.",
          "confidence": 0.02
        }
      ],
      "final_choice": [
        {
          "sheet_name": "Balance Sheet",
          "row_label": "Total Current Assets"
        }
      ],
      "needs_manual_review": false,
      "notes": "Selected the explicit total current assets line."
    },
    {
      "variable": "CHE",
      "candidates": [
        {
          "sheet_name": "Balance Sheet",
          "row_label": "Cash & Short-Term Investments",
          "why": "Includes short-term investments, broader than cash and cash equivalents.",
          "confidence": 0.42
        },
        {
          "sheet_name": "Balance Sheet",
          "row_label": "Cash & Cash Equivalents",
          "why": "Exact match for cash and cash equivalents on the balance sheet.",
          "confidence": 0.99
        },
        {
          "sheet_name": "Balance Sheet",
          "row_label": "Cash & Cash Equivalents - Total",
          "why": "Also an exact cash and cash equivalents total line; useful alternate label across periods.",
          "confidence": 0.97
        },
        {
          "sheet_name": "Balance Sheet",
          "row_label": "Cash & Short Term Investments - Total",
          "why": "Includes short-term investments, so less preferred than pure cash and equivalents.",
          "confidence": 0.4
        },
        {
          "sheet_name": "Balance Sheet",
          "row_label": "Working Capital - Non-Cash",
          "why": "Not cash; opposite concept.",
          "confidence": 0.01
        },
        {
          "sheet_name": "Cash Flow",
          "row_label": "Dividends - Common - Cash Paid",
          "why": "Cash flow item, not balance sheet cash balance.",
          "confidence": 0.01
        },
        {
          "sheet_name": "Cash Flow",
          "row_label": "Cash Dividends Paid & Common Stock Buyback - Net",
          "why": "Financing cash flow metric, not cash balance.",
          "confidence": 0.01
        }
      ],
      "final_choice": [
        {
          "sheet_name": "Balance Sheet",
          "row_label": "Cash & Cash Equivalents"
        },
        {
          "sheet_name": "Balance Sheet",
          "row_label": "Cash & Cash Equivalents - Total"
        }
      ],
      "needs_manual_review": false,
      "notes": "Preferred the pure balance-sheet cash label; included the alternate exact total label as backup for label changes over time."
    },
    {
      "variable": "LCT",
      "candidates": [
        {
          "sheet_name": "Balance Sheet",
          "row_label": "Current Liabilities",
          "why": "Section header for current liabilities, not the reported total value line.",
          "confidence": 0.24
        },
        {
          "sheet_name": "Balance Sheet",
          "row_label": "Other Current Liabilities - Total",
          "why": "Only a component of current liabilities.",
          "confidence": 0.08
        },
        {
          "sheet_name": "Balance Sheet",
          "row_label": "Other Current Liabilities",
          "why": "Only a component of current liabilities.",
          "confidence": 0.06
        },
        {
          "sheet_name": "Balance Sheet",
          "row_label": "Total Current Liabilities",
          "why": "Exact total current liabilities line on the balance sheet.",
          "confidence": 0.99
        },
        {
          "sheet_name": "Balance Sheet",
          "row_label": "Non-Current Liabilities",
          "why": "Wrong maturity bucket.",
          "confidence": 0.01
        },
        {
          "sheet_name": "Balance Sheet",
          "row_label": "Other Non-Current Liabilities - Total",
          "why": "Wrong maturity bucket and only component.",
          "confidence": 0.01
        },
        {
          "sheet_name": "Balance Sheet",
          "row_label": "Other Non-Current Liabilities",
          "why": "Wrong maturity bucket and only component.",
          "confidence": 0.01
        },
        {
          "sheet_name": "Balance Sheet",
          "row_label": "Total Non-Current Liabilities",
          "why": "Wrong maturity bucket.",
          "confidence": 0.01
        }
      ],
      "final_choice": [
        {
          "sheet_name": "Balance Sheet",
          "row_label": "Total Current Liabilities"
        }
      ],
      "needs_manual_review": false,
      "notes": "Selected the explicit total current liabilities line."
    },
    {
      "variable": "STD",
      "candidates": [
        {
          "sheet_name": "Balance Sheet",
          "row_label": "Short-Term Debt & Current Portion of Long-Term Debt",
          "why": "Explicit total for short-term debt/current portion of LTD, but appears to include capitalized leases via component breakdown.",
          "confidence": 0.78
        },
        {
          "sheet_name": "Balance Sheet",
          "row_label": "Short-Term Debt & Notes Payable",
          "why": "Non-lease current borrowings component; suitable as part of summed STD.",
          "confidence": 0.94
        },
        {
          "sheet_name": "Balance Sheet",
          "row_label": "Debt - Long-Term - Maturities - within 1 Year",
          "why": "Current maturities of long-term debt; appears non-lease and suitable as part of summed STD where total line includes leases.",
          "confidence": 0.93
        }
      ],
      "final_choice": [
        {
          "sheet_name": "Balance Sheet",
          "row_label": "Short-Term Debt & Notes Payable"
        },
        {
          "sheet_name": "Balance Sheet",
          "row_label": "Debt - Long-Term - Maturities - within 1 Year"
        }
      ],
      "needs_manual_review": false,
      "notes": "Excluded lease-related current debt per rule. Did not use 'Short-Term Debt & Current Portion of Long-Term Debt' because nearby components indicate it includes capitalized leases, which would overstate baseline STD."
    },
    {
      "variable": "TXP",
      "candidates": [
        {
          "sheet_name": "Balance Sheet",
          "row_label": "Income Taxes - Payable - Short-Term",
          "why": "Explicit current taxes payable line; best match for taxes payable/current tax liabilities.",
          "confidence": 0.98
        }
      ],
      "final_choice": [
        {
          "sheet_name": "Balance Sheet",
          "row_label": "Income Taxes - Payable - Short-Term"
        }
      ],
      "needs_manual_review": false,
      "notes": "Chosen outside shortlist because no TXP candidates were provided, but this is a clear exact match."
    },
    {
      "variable": "PPEGT",
      "candidates": [
        {
          "sheet_name": "Balance Sheet",
          "row_label": "Property, Plant & Equipment - Net - Total",
          "why": "Best reported total PPE line; net total PPE is preferred.",
          "confidence": 0.98
        },
        {
          "sheet_name": "Balance Sheet",
          "row_label": "Property, Plant & Equipment - excluding Assets Leased Out - Net - Total",
          "why": "Also a total net PPE line, but wording is more specialized; less preferred than the generic total.",
          "confidence": 0.86
        },
        {
          "sheet_name": "Balance Sheet",
          "row_label": "Property, Plant & Equipment - Other - Net",
          "why": "Only a component of PPE, not total.",
          "confidence": 0.2
        },
        {
          "sheet_name": "Balance Sheet",
          "row_label": "Property, Plant & Equipment - Gross - Total",
          "why": "Gross PPE total, but net PPE is preferred when available.",
          "confidence": 0.72
        },
        {
          "sheet_name": "Balance Sheet",
          "row_label": "Property, Plant & Equipment - excluding Assets Leased Out - Gross",
          "why": "Gross specialized subtotal; less preferred than net total.",
          "confidence": 0.55
        },
        {
          "sheet_name": "Balance Sheet",
          "row_label": "Property, Plant & Equipment - Other - Gross",
          "why": "Only a component, not total.",
          "confidence": 0.12
        },
        {
          "sheet_name": "Balance Sheet",
          "row_label": "Property, Plant & Equipment - Accumulated Depreciation & Impairment - Total",
          "why": "Contra-asset line, not PPE asset balance.",
          "confidence": 0.01
        },
        {
          "sheet_name": "Balance Sheet",
          "row_label": "Property, Plant & Equipment - excluding Assets Leased Out - Accumulated Depreciation & Impairment - Total",
          "why": "Contra-asset line, not PPE asset balance.",
          "confidence": 0.01
        },
        {
          "sheet_name": "Balance Sheet",
          "row_label": "Property, Plant & Equipment - Other - Accumulated Depreciation & Impairment",
          "why": "Contra-asset component, not PPE asset balance.",
          "confidence": 0.01
        },
        {
          "sheet_name": "Cash Flow",
          "row_label": "Depreciation & Depletion - Property, Plant & Equipment - Cash Flow - to Reconcile",
          "why": "Cash flow reconciliation item, not balance sheet PPE stock.",
          "confidence": 0.01
        },
        {
          "sheet_name": "Cash Flow",
          "row_label": "Property, Plant & Equipment - Purchased/(Sold) - Net - Cash Flow",
          "why": "Cash flow investing item, not balance sheet PPE stock.",
          "confidence": 0.01
        },
        {
          "sheet_name": "Cash Flow",
          "row_label": "Property, Plant & Equipment - Purchased - Cash Flow",
          "why": "Capex flow, not PPE balance.",
          "confidence": 0.01
        },
        {
          "sheet_name": "Cash Flow",
          "row_label": "Property, Plant & Equipment Sold - Cash Flow",
          "why": "Cash flow item, not PPE balance.",
          "confidence": 0.01
        }
      ],
      "final_choice": [
        {
          "sheet_name": "Balance Sheet",
          "row_label": "Property, Plant & Equipment - Net - Total"
        },
        {
          "sheet_name": "Balance Sheet",
          "row_label": "Property, Plant & Equipment - excluding Assets Leased Out - Net - Total"
        }
      ],
      "needs_manual_review": false,
      "notes": "Preferred total net PPE. Included alternate total net PPE label as backup due to possible label variation."
    },
    {
      "variable": "AT",
      "candidates": [
        {
          "sheet_name": "Balance Sheet",
          "row_label": "Right of Use Tangible Assets - Total - Net",
          "why": "Only a component of assets, not total assets.",
          "confidence": 0.03
        },
        {
          "sheet_name": "Balance Sheet",
          "row_label": "Right of Use Tangible Assets - Total - Gross",
          "why": "Only a component of assets, not total assets.",
          "confidence": 0.02
        },
        {
          "sheet_name": "Balance Sheet",
          "row_label": "Intangible Assets - Total - Net",
          "why": "Only a component of assets.",
          "confidence": 0.03
        },
        {
          "sheet_name": "Balance Sheet",
          "row_label": "Total Assets",
          "why": "Exact total assets line on the balance sheet.",
          "confidence": 0.99
        },
        {
          "sheet_name": "Balance Sheet",
          "row_label": "Right of Use Tangible Assets - Total - Net - Supplemental",
          "why": "Supplemental component, not total assets.",
          "confidence": 0.01
        },
        {
          "sheet_name": "Balance Sheet",
          "row_label": "Other Assets - Total",
          "why": "Only a component grouping, not total assets.",
          "confidence": 0.02
        }
      ],
      "final_choice": [
        {
          "sheet_name": "Balance Sheet",
          "row_label": "Total Assets"
        }
      ],
      "needs_manual_review": false,
      "notes": "Selected the explicit total assets line with reported values, not the blank section/header duplicate."
    },
    {
      "variable": "OANCF",
      "candidates": [
        {
          "sheet_name": "Cash Flow",
          "row_label": "Operating Cash Flow - Indirect",
          "why": "Statement section/header, not the net operating cash flow line.",
          "confidence": 0.18
        },
        {
          "sheet_name": "Cash Flow",
          "row_label": "Cash Flow from Operating Activities before Changes in Working Capital",
          "why": "Intermediate subtotal before working capital changes, not final operating cash flow.",
          "confidence": 0.28
        },
        {
          "sheet_name": "Cash Flow",
          "row_label": "Net Cash Flow from Operating Activities",
          "why": "Exact net cash provided by operating activities line; best match for OANCF.",
          "confidence": 0.99
        }
      ],
      "final_choice": [
        {
          "sheet_name": "Cash Flow",
          "row_label": "Net Cash Flow from Operating Activities"
        }
      ],
      "needs_manual_review": false,
      "notes": "Selected the final net operating cash flow line."
    }
  ]
}