{
  "variables": [
    {
      "variable": "REVT",
      "candidates": [
        {
          "sheet_name": "Income Statement",
          "row_label": "Total Revenue",
          "why": "Direct total revenue line; preferable candidate for top-line and matches Net Sales values.",
          "confidence": 0.99
        },
        {
          "sheet_name": "Income Statement",
          "row_label": "Interest Income",
          "why": "Non-operating financial income, not revenue.",
          "confidence": 0.01
        },
        {
          "sheet_name": "Income Statement",
          "row_label": "Income Available to Com Excl ExtraOrd",
          "why": "Net income metric, not revenue.",
          "confidence": 0.01
        },
        {
          "sheet_name": "Income Statement",
          "row_label": "Total comprehensive income for the financial year",
          "why": "Comprehensive income, not revenue.",
          "confidence": 0.01
        },
        {
          "sheet_name": "Income Statement",
          "row_label": "Total comprehensive income",
          "why": "Comprehensive income, not revenue.",
          "confidence": 0.01
        },
        {
          "sheet_name": "Balance Sheet",
          "row_label": "Accrued Income",
          "why": "Balance sheet asset, not revenue.",
          "confidence": 0.01
        },
        {
          "sheet_name": "Balance Sheet",
          "row_label": "Accrued expenses and prepaid income",
          "why": "Balance sheet liability, not revenue.",
          "confidence": 0.01
        }
      ],
      "final_choice": [
        {
          "sheet_name": "Income Statement",
          "row_label": "Total Revenue"
        }
      ],
      "needs_manual_review": false,
      "notes": "Selected the reported total revenue line from the candidate list."
    },
    {
      "variable": "COGS",
      "candidates": [
        {
          "sheet_name": "Income Statement",
          "row_label": "Materials and Services",
          "why": "Best match for direct cost of sales / production inputs.",
          "confidence": 0.95
        }
      ],
      "final_choice": [
        {
          "sheet_name": "Income Statement",
          "row_label": "Materials and Services"
        }
      ],
      "needs_manual_review": false,
      "notes": "Chosen as the closest direct operating cost line."
    },
    {
      "variable": "XSGA_COMPONENTS",
      "candidates": [
        {
          "sheet_name": "Income Statement",
          "row_label": "Employee Benefit Expenses",
          "why": "Personnel/overhead expense; strong SG&A component.",
          "confidence": 0.96
        },
        {
          "sheet_name": "Income Statement",
          "row_label": "Other Operating Expenses",
          "why": "General operating overhead bucket; appropriate SG&A component when no explicit SG&A subtotal exists.",
          "confidence": 0.93
        },
        {
          "sheet_name": "Income Statement",
          "row_label": "Marketing and other sales promotion",
          "why": "Selling expense component, but appears to be a subcomponent of Other Operating Expenses in some years, so selecting both could double count.",
          "confidence": 0.55
        },
        {
          "sheet_name": "Income Statement",
          "row_label": "External services",
          "why": "Administrative/overhead-type component, but appears to be a subcomponent of Other Operating Expenses in some years, so selecting both could double count.",
          "confidence": 0.55
        },
        {
          "sheet_name": "Income Statement",
          "row_label": "Research & Development",
          "why": "Dedicated R&D line exists, but it appears below operating result in the preview order, so it should not be added to XSGA under the stated rule.",
          "confidence": 0.35
        },
        {
          "sheet_name": "Balance Sheet",
          "row_label": "Capitalized Product Development- Net",
          "why": "Balance sheet asset, not SG&A expense.",
          "confidence": 0.01
        },
        {
          "sheet_name": "Balance Sheet",
          "row_label": "Research & Development Costs - Gross",
          "why": "Balance sheet gross asset disclosure, not SG&A expense.",
          "confidence": 0.01
        },
        {
          "sheet_name": "Balance Sheet",
          "row_label": "Capitalized Product Development Expenses",
          "why": "Balance sheet asset, not SG&A expense.",
          "confidence": 0.01
        },
        {
          "sheet_name": "Balance Sheet",
          "row_label": "Research & Development Costs, Gross",
          "why": "Balance sheet asset disclosure, not SG&A expense.",
          "confidence": 0.01
        },
        {
          "sheet_name": "Balance Sheet",
          "row_label": "Acc Amort Research & Development Costs",
          "why": "Balance sheet contra-asset, not SG&A expense.",
          "confidence": 0.01
        },
        {
          "sheet_name": "Balance Sheet",
          "row_label": "Capitalized Product Development",
          "why": "Balance sheet asset, not SG&A expense.",
          "confidence": 0.01
        }
      ],
      "final_choice": [
        {
          "sheet_name": "Income Statement",
          "row_label": "Employee Benefit Expenses"
        },
        {
          "sheet_name": "Income Statement",
          "row_label": "Other Operating Expenses"
        }
      ],
      "needs_manual_review": false,
      "notes": "No explicit SG&A subtotal is shown. Selected the main overhead buckets and avoided Marketing and External services to prevent double counting against Other Operating Expenses. Excluded R&D from XSGA because the only R&D row appears below operating result in the preview order."
    },
    {
      "variable": "XRD",
      "candidates": [
        {
          "sheet_name": "Income Statement",
          "row_label": "Research & Development",
          "why": "Direct dedicated R&D expense line; best match.",
          "confidence": 0.89
        },
        {
          "sheet_name": "Balance Sheet",
          "row_label": "Capitalized Product Development- Net",
          "why": "Balance sheet capitalized development asset, not current-period R&D expense.",
          "confidence": 0.05
        },
        {
          "sheet_name": "Balance Sheet",
          "row_label": "Research & Development Costs - Gross",
          "why": "Balance sheet gross asset disclosure, not expense.",
          "confidence": 0.03
        },
        {
          "sheet_name": "Balance Sheet",
          "row_label": "Research & Development Costs - Accumulated Amortization & Impairment",
          "why": "Balance sheet contra-asset, not R&D expense.",
          "confidence": 0.02
        },
        {
          "sheet_name": "Balance Sheet",
          "row_label": "Capitalized Product Development Expenses",
          "why": "Balance sheet asset, not expense.",
          "confidence": 0.04
        },
        {
          "sheet_name": "Balance Sheet",
          "row_label": "Research & Development Costs, Gross",
          "why": "Balance sheet disclosure, not expense.",
          "confidence": 0.02
        },
        {
          "sheet_name": "Balance Sheet",
          "row_label": "Acc Amort Research & Development Costs",
          "why": "Balance sheet contra-asset, not expense.",
          "confidence": 0.02
        },
        {
          "sheet_name": "Balance Sheet",
          "row_label": "Capitalized Product Development",
          "why": "Balance sheet asset, not expense.",
          "confidence": 0.02
        }
      ],
      "final_choice": [
        {
          "sheet_name": "Income Statement",
          "row_label": "Research & Development"
        }
      ],
      "needs_manual_review": false,
      "notes": "Mapped to the dedicated R&D line. It appears below operating result in the preview order, so it was not also included in XSGA_COMPONENTS."
    },
    {
      "variable": "XINT",
      "candidates": [
        {
          "sheet_name": "Income Statement",
          "row_label": "Financial Expenses",
          "why": "Broad finance-cost bucket, but unpopulated and less granular than available recurring interest components.",
          "confidence": 0.35
        },
        {
          "sheet_name": "Income Statement",
          "row_label": "Interest Expense",
          "why": "Direct interest line in name, but unpopulated here and less informative than populated components.",
          "confidence": 0.45
        },
        {
          "sheet_name": "Income Statement",
          "row_label": "Interest Expenses",
          "why": "Direct interest line in name, but unpopulated here and less informative than populated components.",
          "confidence": 0.45
        },
        {
          "sheet_name": "Income Statement",
          "row_label": "Interest expenses of the financial liabilities measured at amortized cost",
          "why": "Granular recurring interest expense component on debt liabilities.",
          "confidence": 0.94
        },
        {
          "sheet_name": "Income Statement",
          "row_label": "Interest Expense on Financial Lease Liabilities",
          "why": "Granular recurring lease-interest component.",
          "confidence": 0.91
        },
        {
          "sheet_name": "Income Statement",
          "row_label": "Minority Interests",
          "why": "Not interest expense.",
          "confidence": 0.01
        },
        {
          "sheet_name": "Income Statement",
          "row_label": "Minority interests",
          "why": "Not interest expense.",
          "confidence": 0.01
        },
        {
          "sheet_name": "Income Statement",
          "row_label": "Interest Expense on Financial Lease Liabilities - Supplemental",
          "why": "Supplemental duplicate-style disclosure of lease interest; avoid double counting versus the main line.",
          "confidence": 0.2
        },
        {
          "sheet_name": "Balance Sheet",
          "row_label": "Non-controlling interests",
          "why": "Equity line, not interest expense.",
          "confidence": 0.01
        },
        {
          "sheet_name": "Balance Sheet",
          "row_label": "Minority Interest",
          "why": "Equity line, not interest expense.",
          "confidence": 0.01
        }
      ],
      "final_choice": [
        {
          "sheet_name": "Income Statement",
          "row_label": "Interest expenses of the financial liabilities measured at amortized cost"
        },
        {
          "sheet_name": "Income Statement",
          "row_label": "Interest Expense on Financial Lease Liabilities"
        }
      ],
      "needs_manual_review": false,
      "notes": "Used the most granular recurring interest components and excluded total/net finance lines, FX items, balancing values, and supplemental duplicates."
    },
    {
      "variable": "BE",
      "candidates": [
        {
          "sheet_name": "Balance Sheet",
          "row_label": "Invested Non-restricted Equity Fund",
          "why": "Equity component only, not total book equity.",
          "confidence": 0.15
        },
        {
          "sheet_name": "Balance Sheet",
          "row_label": "Equity attributable to shareholders of the Parent company",
          "why": "Best match because BE should exclude non-controlling interests.",
          "confidence": 0.99
        },
        {
          "sheet_name": "Balance Sheet",
          "row_label": "Total equity",
          "why": "Usable only if no parent/owners equity line exists; less preferred here.",
          "confidence": 0.55
        },
        {
          "sheet_name": "Balance Sheet",
          "row_label": "Balancing Item - Shareholders Equity",
          "why": "Balancing line, not appropriate.",
          "confidence": 0.01
        },
        {
          "sheet_name": "Balance Sheet",
          "row_label": "Balancing Item - Total Liability and Equity",
          "why": "Balancing line, not appropriate.",
          "confidence": 0.01
        },
        {
          "sheet_name": "Balance Sheet",
          "row_label": "Total equity and liabilities",
          "why": "Total balance sheet, not equity.",
          "confidence": 0.01
        }
      ],
      "final_choice": [
        {
          "sheet_name": "Balance Sheet",
          "row_label": "Equity attributable to shareholders of the Parent company"
        }
      ],
      "needs_manual_review": false,
      "notes": "Selected owner/parent equity to exclude non-controlling interests from BE."
    },
    {
      "variable": "MIB",
      "candidates": [
        {
          "sheet_name": "Income Statement",
          "row_label": "Minority Interests",
          "why": "Income statement allocation line, not the preferred balance-sheet NCI stock variable.",
          "confidence": 0.1
        },
        {
          "sheet_name": "Income Statement",
          "row_label": "Minority interests",
          "why": "Income statement allocation line, not the preferred balance-sheet NCI stock variable.",
          "confidence": 0.1
        },
        {
          "sheet_name": "Balance Sheet",
          "row_label": "Non-controlling interests",
          "why": "Best balance-sheet label for minority interest / NCI.",
          "confidence": 0.92
        },
        {
          "sheet_name": "Balance Sheet",
          "row_label": "Minority Interest",
          "why": "Alternative balance-sheet label for minority interest.",
          "confidence": 0.85
        }
      ],
      "final_choice": [
        {
          "sheet_name": "Balance Sheet",
          "row_label": "Non-controlling interests"
        },
        {
          "sheet_name": "Balance Sheet",
          "row_label": "Minority Interest"
        }
      ],
      "needs_manual_review": false,
      "notes": "Used balance-sheet NCI labels as a priority list. BE uses parent equity, so this avoids double counting if NCI is present in any year."
    }
  ]
}