{
  "variables": [
    {
      "variable": "ACT",
      "candidates": [
        {
          "sheet_name": "Balance Sheet",
          "row_label": "Total Current Assets",
          "why": "Direct match for total current assets on the balance sheet.",
          "confidence": 0.99
        },
        {
          "sheet_name": "Balance Sheet",
          "row_label": "Total Non-Current Assets",
          "why": "Not current assets; included only because it was in the candidate list.",
          "confidence": 0.01
        }
      ],
      "final_choice": [
        {
          "sheet_name": "Balance Sheet",
          "row_label": "Total Current Assets"
        }
      ],
      "needs_manual_review": false,
      "notes": "Selected the direct total current assets line."
    },
    {
      "variable": "CHE",
      "candidates": [
        {
          "sheet_name": "Balance Sheet",
          "row_label": "Cash and cash equivalents",
          "why": "Direct balance-sheet cash and cash equivalents line, preferred over cash flow presentation lines.",
          "confidence": 0.99
        },
        {
          "sheet_name": "Cash Flow",
          "row_label": "Cash and cash equivalents at end of the period",
          "why": "Cash flow statement ending cash can reconcile to balance-sheet cash, but balance sheet is preferred for CHE.",
          "confidence": 0.75
        },
        {
          "sheet_name": "Cash Flow",
          "row_label": "Cash and cash equivalents at beginning of the pe- riod",
          "why": "Beginning balance, not the balance-sheet cash target.",
          "confidence": 0.1
        },
        {
          "sheet_name": "Cash Flow",
          "row_label": "Cash acquired in a business combination, net",
          "why": "Not a cash balance item.",
          "confidence": 0.01
        },
        {
          "sheet_name": "Cash Flow",
          "row_label": "Effect of exchange rate on cash and cash equivalents",
          "why": "Cash flow adjustment, not the balance-sheet cash balance.",
          "confidence": 0.01
        },
        {
          "sheet_name": "Cash Flow",
          "row_label": "Net (decrease)/increase in cash and cash equiva",
          "why": "Change in cash, not the cash balance.",
          "confidence": 0.01
        },
        {
          "sheet_name": "Cash Flow",
          "row_label": "Net (decrease) in cash and cash equivalents",
          "why": "Change in cash, not the cash balance.",
          "confidence": 0.01
        },
        {
          "sheet_name": "Cash Flow",
          "row_label": "Non-cash disposals of property,  plant and equipment and intangible  assets",
          "why": "Not cash and cash equivalents.",
          "confidence": 0.0
        }
      ],
      "final_choice": [
        {
          "sheet_name": "Balance Sheet",
          "row_label": "Cash and cash equivalents"
        }
      ],
      "needs_manual_review": false,
      "notes": "Used the balance-sheet cash line as required."
    },
    {
      "variable": "LCT",
      "candidates": [
        {
          "sheet_name": "Balance Sheet",
          "row_label": "Total Current Liabilities",
          "why": "Direct match for total current liabilities.",
          "confidence": 0.99
        },
        {
          "sheet_name": "Balance Sheet",
          "row_label": "Balancing Item - Current Liabilities",
          "why": "Balancing line, not preferred when a reported total exists.",
          "confidence": 0.05
        },
        {
          "sheet_name": "Balance Sheet",
          "row_label": "Total Non-Current Liabilities",
          "why": "Not current liabilities.",
          "confidence": 0.01
        }
      ],
      "final_choice": [
        {
          "sheet_name": "Balance Sheet",
          "row_label": "Total Current Liabilities"
        }
      ],
      "needs_manual_review": false,
      "notes": "Selected the reported total current liabilities line."
    },
    {
      "variable": "STD",
      "candidates": [
        {
          "sheet_name": "Balance Sheet",
          "row_label": "Current debt to credit institutions",
          "why": "Clean current financing debt line on the balance sheet; excludes lease liabilities and is preferred as STD.",
          "confidence": 0.98
        },
        {
          "sheet_name": "Balance Sheet",
          "row_label": "Debt - Long-Term - Maturities - within 1 Year",
          "why": "Also represents current maturities of debt, but appears duplicative of the clean current debt line based on identical values in shown years.",
          "confidence": 0.72
        },
        {
          "sheet_name": "Cash Flow",
          "row_label": "Proceeds from Overdraft",
          "why": "Cash flow activity, not a balance-sheet debt balance.",
          "confidence": 0.02
        },
        {
          "sheet_name": "Cash Flow",
          "row_label": "Repayment of overdraft",
          "why": "Cash flow activity, not a balance-sheet debt balance.",
          "confidence": 0.02
        }
      ],
      "final_choice": [
        {
          "sheet_name": "Balance Sheet",
          "row_label": "Current debt to credit institutions"
        }
      ],
      "needs_manual_review": false,
      "notes": "Chose the clean current debt total and excluded lease liabilities. Did not also select 'Debt - Long-Term - Maturities - within 1 Year' to avoid double counting since the values appear duplicative."
    },
    {
      "variable": "TXP",
      "candidates": [
        {
          "sheet_name": "Balance Sheet",
          "row_label": "Current income tax liabilities",
          "why": "Direct match for taxes payable/current tax liabilities payable.",
          "confidence": 0.98
        },
        {
          "sheet_name": "Balance Sheet",
          "row_label": "Current Income tax receivable",
          "why": "Tax receivable is the opposite of taxes payable.",
          "confidence": 0.03
        },
        {
          "sheet_name": "Cash Flow",
          "row_label": "Income Tax Paid",
          "why": "Cash flow payment line, not a balance-sheet payable.",
          "confidence": 0.01
        }
      ],
      "final_choice": [
        {
          "sheet_name": "Balance Sheet",
          "row_label": "Current income tax liabilities"
        }
      ],
      "needs_manual_review": false,
      "notes": "No shortlist candidate was provided, but this exact balance-sheet label is a confident match for TXP."
    },
    {
      "variable": "PPEGT",
      "candidates": [
        {
          "sheet_name": "Balance Sheet",
          "row_label": "Property, Plant & Equipment - Net - Total",
          "why": "Direct total/net PPE line on the balance sheet; preferred for PPEGT.",
          "confidence": 0.99
        },
        {
          "sheet_name": "Balance Sheet",
          "row_label": "Right of Use Tangible Assets - Capital/Finance Lease - Gross",
          "why": "Lease-related asset component, not total PPE.",
          "confidence": 0.15
        },
        {
          "sheet_name": "Balance Sheet",
          "row_label": "Right of Use Tangible Assets - Capital/Finance Lease - Accumulated Depreciation",
          "why": "Contra-asset component, not total PPE.",
          "confidence": 0.05
        },
        {
          "sheet_name": "Balance Sheet",
          "row_label": "Intangible assets",
          "why": "Not PPE.",
          "confidence": 0.01
        },
        {
          "sheet_name": "Cash Flow",
          "row_label": "Disposal of property, plant and equipment",
          "why": "Cash flow line, not balance-sheet PPE balance.",
          "confidence": 0.01
        },
        {
          "sheet_name": "Cash Flow",
          "row_label": "Non-cash disposals of property,  plant and equipment and intangible  assets",
          "why": "Cash flow adjustment, not balance-sheet PPE.",
          "confidence": 0.0
        },
        {
          "sheet_name": "Cash Flow",
          "row_label": "Additions to intangible assets",
          "why": "Not PPE and from cash flow.",
          "confidence": 0.0
        }
      ],
      "final_choice": [
        {
          "sheet_name": "Balance Sheet",
          "row_label": "Property, Plant & Equipment - Net - Total"
        }
      ],
      "needs_manual_review": false,
      "notes": "Selected the total net PPE line, which best matches PPEGT."
    },
    {
      "variable": "AT",
      "candidates": [
        {
          "sheet_name": "Balance Sheet",
          "row_label": "Total Assets",
          "why": "Direct match for total assets.",
          "confidence": 0.99
        }
      ],
      "final_choice": [
        {
          "sheet_name": "Balance Sheet",
          "row_label": "Total Assets"
        }
      ],
      "needs_manual_review": false,
      "notes": "Selected the reported total assets line."
    },
    {
      "variable": "OANCF",
      "candidates": [
        {
          "sheet_name": "Cash Flow",
          "row_label": "Net cash provided by operating activities",
          "why": "Direct match for net cash flow from operating activities.",
          "confidence": 0.99
        }
      ],
      "final_choice": [
        {
          "sheet_name": "Cash Flow",
          "row_label": "Net cash provided by operating activities"
        }
      ],
      "needs_manual_review": false,
      "notes": "Direct operating cash flow line from the cash flow statement."
    }
  ]
}